[
  {
    "brand": "Staedtler",
    "size": "15 cm",
    "price": 5000
  },
  {
    "brand": "Faber-Castell",
    "size": "30 cm",
    "price": 8000
  },
  {
    "brand": "Maped",
    "size": "20 cm",
    "price": 3500
  },
  {
    "brand": "Casio",
    "size": "50 cm",
    "price": 10000
  },
  {
    "brand": "Rotring",
    "size": "40 cm",
    "price": 12000
  },
  {
    "brand": "Stabilo",
    "size": "25 cm",
    "price": 4500
  },
  {
    "brand": "Pentel",
    "size": "35 cm",
    "price": 6000
  },
  {
    "brand": "Koh-i-Noor",
    "size": "45 cm",
    "price": 9000
  },
  {
    "brand": "Maped Helix",
    "size": "60 cm",
    "price": 15000
  },
  {
    "brand": "Artline",
    "size": "55 cm",
    "price": 13000
  }
]
